{
  "version": "1.8.0",
  "export_type": "topic_bundle",
  "terms": [
    {
      "taxonomy": "topic",
      "language": "English",
      "language_code": "01EN",
      "name": "UPPSC 2021 GS Paper-2 Hindi (हिंदी व्याकरण)",
      "slug": "hindi-vyakaran-uppsc-2021"
    }
  ],
  "posts": [
    {
      "id": 4001,
      "post_author": 1,
      "post_date": "2026-07-18 10:00:00",
      "post_title": "सारणी – 1 से सारणी – 2 का सही मिलान कीजिए तथा कूट से ...",
      "post_content": "सारणी – 1 से सारणी – 2 का सही मिलान कीजिए तथा कूट से सही विकल्प का चयन कीजिए ।<br><table border='1' cellpadding='6' cellspacing='0' style='border-collapse:collapse;text-align:center'><tr><th>सारणी-1</th><th>सारणी-2</th></tr><tr><td>A. अल्पविराम</td><td>1. –</td></tr><tr><td>B. कोष्ठक</td><td>2. ०</td></tr><tr><td>C. संक्षेपसूचक</td><td>3. ,</td></tr><tr><td>D. योजक</td><td>4. ( )</td></tr></table>",
      "post_status": "publish",
      "post_type": "question",
      "meta_input": {
        "_aimcq_options": [
          {
            "text": "A-2, B-1, C-3, D-4",
            "image": ""
          },
          {
            "text": "A-3, B-2, C-4, D-1",
            "image": ""
          },
          {
            "text": "A-1, B-3, C-2, D-4",
            "image": ""
          },
          {
            "text": "A-3, B-4, C-2, D-1",
            "image": ""
          }
        ],
        "_aimcq_explanation": "<p>यहाँ हमें हर विराम-चिह्न के नाम को उसके सही प्रतीक (चिह्न) से मिलाना है।</p><p><b>एक-एक जोड़ी मिलाएँ:</b><br>- अल्पविराम (A) → , (3), वाक्य में छोटा-सा ठहराव दिखाने वाला चिह्न<br>- कोष्ठक (B) → ( ) (4), किसी अतिरिक्त जानकारी को घेरने वाला चिह्न<br>- संक्षेपसूचक (C) → ० (2), किसी शब्द के संक्षिप्त रूप को दर्शाने वाला चिह्न (जैसे 'डॉ०')<br>- योजक (D) → – (1), दो शब्दों को जोड़ने वाला चिह्न (हाइफ़न)</p><p><b>याद रखने की तरकीब:</b> हर विराम-चिह्न के नाम में ही उसका संकेत छुपा है - 'योजक' माने जोड़ने वाला (–), 'कोष्ठक' माने घेरने वाला (( ))। इसलिए सही उत्तर <b>A-3, B-4, C-2, D-1</b> है।</p>",
        "_aimcq_correct_answers": [
          3
        ]
      },
      "taxonomies": {
        "topic": [
          "hindi-vyakaran-uppsc-2021"
        ]
      },
      "embedded_media": []
    },
    {
      "id": 4002,
      "post_author": 1,
      "post_date": "2026-07-18 10:00:00",
      "post_title": "'उत्कर्ष' का विलोम है",
      "post_content": "'उत्कर्ष' का विलोम है",
      "post_status": "publish",
      "post_type": "question",
      "meta_input": {
        "_aimcq_options": [
          {
            "text": "निष्कर्ष",
            "image": ""
          },
          {
            "text": "उपकर्ष",
            "image": ""
          },
          {
            "text": "अपकर्ष",
            "image": ""
          },
          {
            "text": "उत्सर्ग",
            "image": ""
          }
        ],
        "_aimcq_explanation": "<p>'उत्कर्ष' शब्द का अर्थ है उन्नति, ऊँचाई या उत्थान। इसका सही विलोम वह शब्द होगा जिसका अर्थ पतन या गिरावट हो।</p><p><b>एक-एक विकल्प जाँचें:</b><br>- निष्कर्ष → इसका अर्थ है परिणाम/निचोड़, यह 'उत्कर्ष' का विलोम नहीं है ✘<br>- उपकर्ष → यह मानक हिन्दी शब्द नहीं है, विलोम के रूप में प्रचलित नहीं ✘<br>- अपकर्ष → इसका अर्थ है अवनति/पतन, जो 'उत्कर्ष' (उन्नति) का सीधा विपरीत है ✔<br>- उत्सर्ग → इसका अर्थ है त्याग, यह भी 'उत्कर्ष' का विलोम नहीं है ✘</p><p><b>याद रखने की तरकीब:</b> उत्कर्ष = उन्नति, अपकर्ष = अवनति - दोनों में 'कर्ष' मूल शब्द एक ही है, बस उपसर्ग बदलने से अर्थ विपरीत हो जाता है। इसलिए सही उत्तर <b>'अपकर्ष'</b> है।</p>",
        "_aimcq_correct_answers": [
          2
        ]
      },
      "taxonomies": {
        "topic": [
          "hindi-vyakaran-uppsc-2021"
        ]
      },
      "embedded_media": []
    },
    {
      "id": 4003,
      "post_author": 1,
      "post_date": "2026-07-18 10:00:00",
      "post_title": "'आजीवन' में समास है",
      "post_content": "'आजीवन' में समास है",
      "post_status": "publish",
      "post_type": "question",
      "meta_input": {
        "_aimcq_options": [
          {
            "text": "तत्पुरुष",
            "image": ""
          },
          {
            "text": "अव्ययीभाव",
            "image": ""
          },
          {
            "text": "द्वंद्व",
            "image": ""
          },
          {
            "text": "कर्मधारय",
            "image": ""
          }
        ],
        "_aimcq_explanation": "<p>'आजीवन' शब्द 'आ' उपसर्ग और 'जीवन' शब्द से मिलकर बना है, जिसका अर्थ है 'जीवन भर' या 'जीवन-पर्यन्त'।</p><p><b>पहचान:</b> जिस समास में पूर्वपद अव्यय होता है और पूरा पद भी अव्यय की तरह प्रयोग होता है, वह <b>अव्ययीभाव समास</b> कहलाता है। यहाँ 'आ' अव्यय है और पूरा शब्द 'आजीवन' भी क्रिया-विशेषण (अव्यय) की तरह प्रयुक्त होता है, जैसे 'आजीवन कारावास'।</p><p><b>अन्य विकल्प क्यों नहीं:</b> तत्पुरुष, द्वंद्व और कर्मधारय समास में दोनों पद संज्ञा/विशेषण होते हैं, यहाँ पहला पद अव्यय है, इसलिए ये लागू नहीं होते।</p><p><b>याद रखने की तरकीब:</b> जहाँ भी शब्द के शुरू में 'आ', 'यथा', 'प्रति' जैसे अव्यय जुड़कर पूरा शब्द क्रिया-विशेषण बन जाए, वहाँ अव्ययीभाव समास समझें। इसलिए सही उत्तर <b>'अव्ययीभाव'</b> है।</p>",
        "_aimcq_correct_answers": [
          1
        ]
      },
      "taxonomies": {
        "topic": [
          "hindi-vyakaran-uppsc-2021"
        ]
      },
      "embedded_media": []
    },
    {
      "id": 4004,
      "post_author": 1,
      "post_date": "2026-07-18 10:00:00",
      "post_title": "'जिजीविषा' का अर्थ है",
      "post_content": "'जिजीविषा' का अर्थ है",
      "post_status": "publish",
      "post_type": "question",
      "meta_input": {
        "_aimcq_options": [
          {
            "text": "जीने की इच्छा",
            "image": ""
          },
          {
            "text": "जीतने की इच्छा",
            "image": ""
          },
          {
            "text": "परोपकार की इच्छा",
            "image": ""
          },
          {
            "text": "प्रबल इच्छा",
            "image": ""
          }
        ],
        "_aimcq_explanation": "<p>'जिजीविषा' शब्द संस्कृत की 'जीव्' धातु से इच्छार्थक प्रत्यय जोड़कर बना है।</p><p><b>एक-एक विकल्प जाँचें:</b><br>- जीने की इच्छा → यही 'जिजीविषा' का सही और मानक अर्थ है ✔<br>- जीतने की इच्छा → इसके लिए हिन्दी शब्द 'जिगीषा' है, 'जिजीविषा' नहीं ✘<br>- परोपकार की इच्छा → यह अर्थ 'जिजीविषा' से मेल नहीं खाता ✘<br>- प्रबल इच्छा → यह सामान्य अर्थ है, विशिष्ट अर्थ नहीं ✘</p><p><b>याद रखने की तरकीब:</b> 'जिजीविषा' में 'जीव' (जीना) शब्द छुपा है, इसलिए इसका अर्थ 'जीने की इच्छा' है - इसे 'जिगीषा' (जीतने की इच्छा) से भ्रमित न करें। इसलिए सही उत्तर <b>'जीने की इच्छा'</b> है।</p>",
        "_aimcq_correct_answers": [
          0
        ]
      },
      "taxonomies": {
        "topic": [
          "hindi-vyakaran-uppsc-2021"
        ]
      },
      "embedded_media": []
    },
    {
      "id": 4005,
      "post_author": 1,
      "post_date": "2026-07-18 10:00:00",
      "post_title": "'उसने नहाकर भोजन किया' – वाक्य में 'नहाकर' किस क्रिया का ...",
      "post_content": "'उसने नहाकर भोजन किया' – वाक्य में 'नहाकर' किस क्रिया का उदाहरण है ?",
      "post_status": "publish",
      "post_type": "question",
      "meta_input": {
        "_aimcq_options": [
          {
            "text": "प्रेरणार्थक",
            "image": ""
          },
          {
            "text": "द्विकर्मक",
            "image": ""
          },
          {
            "text": "संयुक्त",
            "image": ""
          },
          {
            "text": "पूर्वकालिक",
            "image": ""
          }
        ],
        "_aimcq_explanation": "<p>जब क्रिया के मूल रूप में 'कर' या 'करके' जोड़कर यह बताया जाता है कि एक काम पहले पूरा हुआ, फिर दूसरा काम हुआ, तो वह <b>पूर्वकालिक क्रिया</b> कहलाती है।</p><p><b>विश्लेषण:</b> 'नहाकर भोजन किया' में पहले 'नहाना' काम हुआ, उसके बाद 'भोजन करना' काम हुआ - यानी 'नहाकर' यह दिखा रहा है कि यह क्रिया मुख्य क्रिया (भोजन किया) से पहले पूरी हो चुकी थी।</p><p><b>अन्य विकल्प क्यों नहीं:</b> प्रेरणार्थक क्रिया में किसी को कुछ करने के लिए प्रेरित किया जाता है, द्विकर्मक में दो कर्म होते हैं, संयुक्त क्रिया में दो क्रियाएँ मिलकर एक भाव देती हैं - इनमें से कोई भी यहाँ लागू नहीं होता।</p><p><b>याद रखने की तरकीब:</b> क्रिया के साथ 'कर/करके' जुड़ा दिखे और वह पहले पूरा हो चुका काम बताए, तो समझ जाइए वह पूर्वकालिक क्रिया है। इसलिए सही उत्तर <b>'पूर्वकालिक'</b> है।</p>",
        "_aimcq_correct_answers": [
          3
        ]
      },
      "taxonomies": {
        "topic": [
          "hindi-vyakaran-uppsc-2021"
        ]
      },
      "embedded_media": []
    },
    {
      "id": 4006,
      "post_author": 1,
      "post_date": "2026-07-18 10:00:00",
      "post_title": "'बहती गंगा में हाथ धोना' – मुहावरे का सही अर्थ है",
      "post_content": "'बहती गंगा में हाथ धोना' – मुहावरे का सही अर्थ है",
      "post_status": "publish",
      "post_type": "question",
      "meta_input": {
        "_aimcq_options": [
          {
            "text": "अवसर खो देना",
            "image": ""
          },
          {
            "text": "अवसर का लाभ उठाना",
            "image": ""
          },
          {
            "text": "अवसर की परवाह करना",
            "image": ""
          },
          {
            "text": "अवसर को पहचानना",
            "image": ""
          }
        ],
        "_aimcq_explanation": "<p>यह एक प्रचलित मुहावरा है, जिसमें बिना किसी विशेष मेहनत के मिले हुए अवसर का फायदा उठाने की बात कही जाती है।</p><p><b>अर्थ:</b> जैसे बहती हुई गंगा में हाथ धोना आसान और स्वाभाविक होता है (क्योंकि पानी पहले से ही बह रहा है), वैसे ही जब कोई अनुकूल परिस्थिति या मौका पहले से मौजूद हो, तो उसका लाभ उठा लेना ही इस मुहावरे का भाव है।</p><p><b>अन्य विकल्प क्यों नहीं:</b> यह मुहावरा 'अवसर खो देना', 'परवाह करना' या 'पहचानना' का भाव नहीं देता, बल्कि सीधे-सीधे उपलब्ध अवसर का उपयोग करने की बात कहता है।</p><p><b>याद रखने की तरकीब:</b> 'बहती गंगा' यानी पहले से उपलब्ध साधन/मौका, और 'हाथ धोना' यानी उसका फायदा उठाना। इसलिए सही उत्तर <b>'अवसर का लाभ उठाना'</b> है।</p>",
        "_aimcq_correct_answers": [
          1
        ]
      },
      "taxonomies": {
        "topic": [
          "hindi-vyakaran-uppsc-2021"
        ]
      },
      "embedded_media": []
    },
    {
      "id": 4007,
      "post_author": 1,
      "post_date": "2026-07-18 10:00:00",
      "post_title": "'गमन' शब्द को विपरीतार्थक बनाने के लिए इनमें से किस ...",
      "post_content": "'गमन' शब्द को विपरीतार्थक बनाने के लिए इनमें से किस उपसर्ग का प्रयोग शुद्ध है ?",
      "post_status": "publish",
      "post_type": "question",
      "meta_input": {
        "_aimcq_options": [
          {
            "text": "अनु",
            "image": ""
          },
          {
            "text": "आ",
            "image": ""
          },
          {
            "text": "उप",
            "image": ""
          },
          {
            "text": "परि",
            "image": ""
          }
        ],
        "_aimcq_explanation": "<p>'गमन' का अर्थ है जाना। इसका विपरीतार्थक शब्द 'आगमन' है, जिसका अर्थ है आना।</p><p><b>एक-एक विकल्प जाँचें:</b><br>- अनु + गमन = अनुगमन (पीछे-पीछे चलना) - यह विपरीतार्थक नहीं, बल्कि एक नया भाव देता है ✘<br>- आ + गमन = आगमन (आना) - यह 'गमन' (जाना) का सही विपरीतार्थक है ✔<br>- उप + गमन = उपगमन - यह मानक विपरीतार्थक रूप नहीं है ✘<br>- परि + गमन = परिगमन - यह भी विपरीतार्थक भाव नहीं देता ✘</p><p><b>याद रखने की तरकीब:</b> 'आ' उपसर्ग प्रायः किसी दिशा की ओर आने का भाव देता है (जैसे आगमन, आकर्षण), जबकि 'गमन' जाने का भाव देता है - इसलिए दोनों एक-दूसरे के विपरीत हैं। इसलिए सही उत्तर <b>'आ'</b> है।</p>",
        "_aimcq_correct_answers": [
          1
        ]
      },
      "taxonomies": {
        "topic": [
          "hindi-vyakaran-uppsc-2021"
        ]
      },
      "embedded_media": []
    },
    {
      "id": 4008,
      "post_author": 1,
      "post_date": "2026-07-18 10:00:00",
      "post_title": "शब्द चयन की दृष्टि से इनमें एक शुद्ध वाक्य है",
      "post_content": "शब्द चयन की दृष्टि से इनमें एक शुद्ध वाक्य है",
      "post_status": "publish",
      "post_type": "question",
      "meta_input": {
        "_aimcq_options": [
          {
            "text": "रवीन्द्रनाथ टैगोर की कुछ रचनाओं का नागरी भाषा में अनुवाद हुआ है ।",
            "image": ""
          },
          {
            "text": "राजा हरिश्चन्द्र के सदृश्य कोई सत्यवादी नहीं हुआ ।",
            "image": ""
          },
          {
            "text": "पद्य के चौथे भाग को चरण कहते हैं ।",
            "image": ""
          },
          {
            "text": "रामचन्द्र शुक्ल ने अनेक ग्रन्थों की रचना की ।",
            "image": ""
          }
        ],
        "_aimcq_explanation": "<p>इस प्रश्न में हमें हर वाक्य में प्रयुक्त शब्दों की शुद्धता की जाँच करनी है।</p><p><b>एक-एक विकल्प जाँचें:</b><br>- 'नागरी भाषा' → 'नागरी' एक लिपि (देवनागरी लिपि) है, भाषा नहीं, इसलिए यह शब्द-प्रयोग अशुद्ध है ✘<br>- 'सदृश्य' → सही शब्द 'सदृश' है (य अतिरिक्त लगाना अशुद्ध है) ✘<br>- 'चरण' → पद्य के चौथे भाग के लिए यहाँ अपेक्षित मानक शब्द से यह मेल नहीं खाता ✘<br>- रामचन्द्र शुक्ल ने अनेक ग्रन्थों की रचना की । → इस वाक्य में शब्द-प्रयोग व्याकरण और अर्थ दोनों दृष्टि से पूर्णतः शुद्ध है ✔</p><p><b>याद रखने की तरकीब:</b> शब्द-चयन शुद्धता जाँचते समय ध्यान दें कि कहीं भाषा और लिपि, या समान लगने वाले शब्दों (सदृश/सदृश्य) में गड़बड़ी तो नहीं हो रही। इसलिए सही उत्तर <b>'रामचन्द्र शुक्ल ने अनेक ग्रन्थों की रचना की ।'</b> है।</p>",
        "_aimcq_correct_answers": [
          3
        ]
      },
      "taxonomies": {
        "topic": [
          "hindi-vyakaran-uppsc-2021"
        ]
      },
      "embedded_media": []
    },
    {
      "id": 4009,
      "post_author": 1,
      "post_date": "2026-07-18 10:00:00",
      "post_title": "'स्वार्थ' में निम्नलिखित में से कौन-सी संधि है ?",
      "post_content": "'स्वार्थ' में निम्नलिखित में से कौन-सी संधि है ?",
      "post_status": "publish",
      "post_type": "question",
      "meta_input": {
        "_aimcq_options": [
          {
            "text": "दीर्घ",
            "image": ""
          },
          {
            "text": "यण",
            "image": ""
          },
          {
            "text": "वृद्धि",
            "image": ""
          },
          {
            "text": "गुण",
            "image": ""
          }
        ],
        "_aimcq_explanation": "<p>'स्वार्थ' शब्द = 'स्व' + 'अर्थ' से मिलकर बना है।</p><p><b>विश्लेषण:</b> यहाँ 'स्व' के अंत में 'अ' स्वर है और 'अर्थ' के शुरू में भी 'अ' स्वर है। नियमानुसार अ/आ + अ/आ = आ होता है, यानी 'अ' + 'अ' मिलकर 'आ' बनता है (स्व + अर्थ = स्वार्थ)। यह नियम <b>दीर्घ संधि</b> कहलाता है।</p><p><b>अन्य विकल्प क्यों नहीं:</b> यण संधि में इ/ई/उ/ऊ/ऋ के बाद असमान स्वर आता है, गुण संधि में अ/आ के बाद इ-ई/उ-ऊ/ऋ आता है, वृद्धि संधि में अ/आ के बाद ए-ऐ/ओ-औ आता है - इनमें से कोई भी नियम यहाँ लागू नहीं होता, क्योंकि यहाँ दोनों तरफ 'अ' स्वर है।</p><p><b>याद रखने की तरकीब:</b> जब भी दो समान स्वर (अ+अ, आ+आ, अ+आ आदि) मिलकर दीर्घ स्वर बनाएँ, वह दीर्घ संधि होती है। इसलिए सही उत्तर <b>'दीर्घ'</b> है।</p>",
        "_aimcq_correct_answers": [
          0
        ]
      },
      "taxonomies": {
        "topic": [
          "hindi-vyakaran-uppsc-2021"
        ]
      },
      "embedded_media": []
    },
    {
      "id": 4010,
      "post_author": 1,
      "post_date": "2026-07-18 10:00:00",
      "post_title": "महत्त्वपूर्ण कृति 'कृष्णायन' उत्तर प्रदेश की बोलियों में से ...",
      "post_content": "महत्त्वपूर्ण कृति 'कृष्णायन' उत्तर प्रदेश की बोलियों में से किस बोली में लिखी गयी है ?",
      "post_status": "publish",
      "post_type": "question",
      "meta_input": {
        "_aimcq_options": [
          {
            "text": "खड़ी बोली में",
            "image": ""
          },
          {
            "text": "अवधी बोली में",
            "image": ""
          },
          {
            "text": "ब्रज बोली में",
            "image": ""
          },
          {
            "text": "बघेली बोली में",
            "image": ""
          }
        ],
        "_aimcq_explanation": "<p>'कृष्णायन' हिन्दी साहित्य की एक प्रसिद्ध काव्य-कृति है, जो पूर्वी हिन्दी की अवधी बोली की परंपरा से जुड़ी मानी जाती है।</p><p><b>एक-एक विकल्प जाँचें:</b><br>- खड़ी बोली → यह आधुनिक मानक हिन्दी की बोली है, 'कृष्णायन' इसमें नहीं रची गई ✘<br>- अवधी बोली → यही सही उत्तर है, यह कृति अवधी बोली में लिखी गई मानी जाती है ✔<br>- ब्रज बोली → यह कृष्ण-भक्ति काव्य की प्रमुख बोली है, पर यह कृति इस बोली में नहीं है ✘<br>- बघेली बोली → यह पूर्वी हिन्दी की एक उपबोली है, पर यह कृति इसमें नहीं है ✘</p><p><b>याद रखने की तरकीब:</b> उत्तर प्रदेश की प्रमुख साहित्यिक कृतियों और उनकी बोली को जोड़े में याद रखना परीक्षा में उपयोगी रहता है। इसलिए सही उत्तर <b>'अवधी बोली में'</b> है।</p>",
        "_aimcq_correct_answers": [
          1
        ]
      },
      "taxonomies": {
        "topic": [
          "hindi-vyakaran-uppsc-2021"
        ]
      },
      "embedded_media": []
    },
    {
      "id": 4011,
      "post_author": 1,
      "post_date": "2026-07-18 10:00:00",
      "post_title": "निम्नलिखित में से सही युग्म चुनिए ।",
      "post_content": "निम्नलिखित में से सही युग्म चुनिए ।",
      "post_status": "publish",
      "post_type": "question",
      "meta_input": {
        "_aimcq_options": [
          {
            "text": "गलीचा – पुर्तगाली",
            "image": ""
          },
          {
            "text": "आमदनी – फारसी",
            "image": ""
          },
          {
            "text": "अंग्रेज़ – फ्रेंच",
            "image": ""
          },
          {
            "text": "पादरी – तुर्की",
            "image": ""
          }
        ],
        "_aimcq_explanation": "<p>हिन्दी में कई शब्द विदेशी भाषाओं से आए हैं। इस प्रश्न में हमें शब्द और उसकी सही मूल भाषा का जोड़ा पहचानना है।</p><p><b>एक-एक विकल्प जाँचें:</b><br>- गलीचा – पुर्तगाली → 'गलीचा' वास्तव में फ़ारसी मूल का शब्द है, पुर्तगाली नहीं ✘<br>- आमदनी – फारसी → 'आमदनी' शब्द फ़ारसी भाषा से आया है, यह सही जोड़ी है ✔<br>- अंग्रेज़ – फ्रेंच → 'अंग्रेज़' शब्द पुर्तगाली भाषा से आया माना जाता है, फ्रेंच से नहीं ✘<br>- पादरी – तुर्की → 'पादरी' शब्द पुर्तगाली भाषा का है, तुर्की का नहीं ✘</p><p><b>याद रखने की तरकीब:</b> प्रशासन, आमदनी, दुकान जैसे रोज़मर्रा के शब्द अक्सर फ़ारसी मूल के होते हैं। इसलिए सही उत्तर <b>'आमदनी – फारसी'</b> है।</p>",
        "_aimcq_correct_answers": [
          1
        ]
      },
      "taxonomies": {
        "topic": [
          "hindi-vyakaran-uppsc-2021"
        ]
      },
      "embedded_media": []
    },
    {
      "id": 4012,
      "post_author": 1,
      "post_date": "2026-07-18 10:00:00",
      "post_title": "'अज' का अर्थ नहीं है",
      "post_content": "'अज' का अर्थ नहीं है",
      "post_status": "publish",
      "post_type": "question",
      "meta_input": {
        "_aimcq_options": [
          {
            "text": "जिसका जन्म न हो",
            "image": ""
          },
          {
            "text": "दशरथ के पिता",
            "image": ""
          },
          {
            "text": "मोती",
            "image": ""
          },
          {
            "text": "ब्रह्मा, विष्णु, शिव",
            "image": ""
          }
        ],
        "_aimcq_explanation": "<p>'अज' एक अनेकार्थी शब्द है, जिसके संस्कृत में कई अर्थ प्रचलित हैं।</p><p><b>एक-एक विकल्प जाँचें:</b><br>- जिसका जन्म न हो → यह 'अज' का शाब्दिक/मूल अर्थ है (अ + ज = जिसका जन्म न हो) ✔ (सही अर्थ है)<br>- दशरथ के पिता → पौराणिक संदर्भ में 'अज' राजा दशरथ के पिता का नाम भी है ✔ (सही अर्थ है)<br>- मोती → 'अज' का यह अर्थ प्रचलित नहीं है, यह अर्थ 'अज' से मेल नहीं खाता ✘ (यही अर्थ नहीं है)<br>- ब्रह्मा, विष्णु, शिव → चूँकि ये तीनों देवता अजन्मे (अनादि) माने जाते हैं, इसलिए 'अज' इनके लिए भी प्रयुक्त होता है ✔ (सही अर्थ है)</p><p><b>याद रखने की तरकीब:</b> 'अज' के सभी वास्तविक अर्थ 'जन्म न होने' के भाव से जुड़े हैं (चाहे वह देवता हों या राजा दशरथ के पिता), जबकि 'मोती' का इससे कोई संबंध नहीं। इसलिए सही उत्तर (जो अर्थ नहीं है) <b>'मोती'</b> है।</p>",
        "_aimcq_correct_answers": [
          2
        ]
      },
      "taxonomies": {
        "topic": [
          "hindi-vyakaran-uppsc-2021"
        ]
      },
      "embedded_media": []
    },
    {
      "id": 4013,
      "post_author": 1,
      "post_date": "2026-07-18 10:00:00",
      "post_title": "निम्नलिखित में 'देवता' का पर्यायवाची शब्द है",
      "post_content": "निम्नलिखित में 'देवता' का पर्यायवाची शब्द है",
      "post_status": "publish",
      "post_type": "question",
      "meta_input": {
        "_aimcq_options": [
          {
            "text": "किंकर",
            "image": ""
          },
          {
            "text": "विबुध",
            "image": ""
          },
          {
            "text": "विपुल",
            "image": ""
          },
          {
            "text": "लोकेश",
            "image": ""
          }
        ],
        "_aimcq_explanation": "<p>पर्यायवाची शब्द वे होते हैं जिनका अर्थ एक जैसा होता है। यहाँ हमें 'देवता' के समान अर्थ वाला शब्द ढूँढना है।</p><p><b>एक-एक विकल्प जाँचें:</b><br>- किंकर → इसका अर्थ है सेवक/दास, यह 'देवता' का पर्यायवाची नहीं है ✘<br>- विबुध → इसका अर्थ भी 'देवता' ही होता है (वि + बुध = विशेष रूप से बुद्धिमान, देवताओं के लिए प्रयुक्त) ✔<br>- विपुल → इसका अर्थ है अत्यधिक/बहुत, यह 'देवता' का पर्यायवाची नहीं है ✘<br>- लोकेश → इसका अर्थ है संसार का स्वामी, यह सामान्यतः 'देवता' का सीधा पर्याय नहीं माना जाता ✘</p><p><b>याद रखने की तरकीब:</b> 'देवता' के प्रमुख पर्यायवाची हैं - सुर, विबुध, अमर, निर्जर आदि। इसलिए सही उत्तर <b>'विबुध'</b> है।</p>",
        "_aimcq_correct_answers": [
          1
        ]
      },
      "taxonomies": {
        "topic": [
          "hindi-vyakaran-uppsc-2021"
        ]
      },
      "embedded_media": []
    },
    {
      "id": 4014,
      "post_author": 1,
      "post_date": "2026-07-18 10:00:00",
      "post_title": "'हो सकता है वह आया हो' – वाक्य है",
      "post_content": "'हो सकता है वह आया हो' – वाक्य है",
      "post_status": "publish",
      "post_type": "question",
      "meta_input": {
        "_aimcq_options": [
          {
            "text": "अनिश्चित वर्तमान",
            "image": ""
          },
          {
            "text": "सन्दिग्ध वर्तमान",
            "image": ""
          },
          {
            "text": "सम्भाव्य वर्तमान",
            "image": ""
          },
          {
            "text": "अपूर्ण वर्तमान",
            "image": ""
          }
        ],
        "_aimcq_explanation": "<p>वर्तमान काल के कई भेद होते हैं, जो क्रिया की निश्चितता, संभावना या संदेह को दर्शाते हैं।</p><p><b>विश्लेषण:</b> 'हो सकता है वह आया हो' वाक्य में 'हो सकता है' के प्रयोग से यह पता चलता है कि काम के होने की केवल संभावना जताई जा रही है, निश्चितता नहीं। ऐसी क्रिया को <b>सम्भाव्य वर्तमान</b> कहते हैं।</p><p><b>अन्य विकल्प क्यों नहीं:</b> अनिश्चित वर्तमान में काम के समय की अनिश्चितता होती है, सन्दिग्ध वर्तमान में संदेह का भाव होता है और अपूर्ण वर्तमान में कार्य अभी अधूरा रहता है - यहाँ मुख्य भाव संभावना का है, इसलिए यह सम्भाव्य वर्तमान की श्रेणी में आता है।</p><p><b>याद रखने की तरकीब:</b> जहाँ भी वाक्य में 'हो सकता है/शायद' जैसे शब्दों से संभावना जताई जाए, वह सम्भाव्य वर्तमान कहलाता है। इसलिए सही उत्तर <b>'सम्भाव्य वर्तमान'</b> है।</p>",
        "_aimcq_correct_answers": [
          2
        ]
      },
      "taxonomies": {
        "topic": [
          "hindi-vyakaran-uppsc-2021"
        ]
      },
      "embedded_media": []
    },
    {
      "id": 4015,
      "post_author": 1,
      "post_date": "2026-07-18 10:00:00",
      "post_title": "निम्नलिखित में से शुद्ध वर्तनी वाला शब्द है",
      "post_content": "निम्नलिखित में से शुद्ध वर्तनी वाला शब्द है",
      "post_status": "publish",
      "post_type": "question",
      "meta_input": {
        "_aimcq_options": [
          {
            "text": "कवयत्री",
            "image": ""
          },
          {
            "text": "घनिष्ठ",
            "image": ""
          },
          {
            "text": "चिन्ह",
            "image": ""
          },
          {
            "text": "ईर्षा",
            "image": ""
          }
        ],
        "_aimcq_explanation": "<p>वर्तनी (spelling) की शुद्धता जाँचने के लिए हर शब्द के मानक रूप को याद रखना ज़रूरी है।</p><p><b>एक-एक विकल्प जाँचें:</b><br>- कवयत्री → सही मानक वर्तनी 'कवयित्री' होती है, यह रूप अशुद्ध है ✘<br>- घनिष्ठ → यह शब्द अपने मानक/शुद्ध रूप में ही लिखा गया है ✔<br>- चिन्ह → सही मानक वर्तनी 'चिह्न' होती है (न और ह का क्रम बदला है), यह रूप अशुद्ध है ✘<br>- ईर्षा → सही मानक वर्तनी 'ईर्ष्या' होती है, यह रूप अशुद्ध है ✘</p><p><b>याद रखने की तरकीब:</b> जिन शब्दों में संयुक्ताक्षर (ष्या, ह्न आदि) का क्रम गड़बड़ा जाए, वहीं वर्तनी की गलती छुपी होती है - 'चिन्ह' नहीं 'चिह्न', 'ईर्षा' नहीं 'ईर्ष्या'। इसलिए सही उत्तर <b>'घनिष्ठ'</b> है।</p>",
        "_aimcq_correct_answers": [
          1
        ]
      },
      "taxonomies": {
        "topic": [
          "hindi-vyakaran-uppsc-2021"
        ]
      },
      "embedded_media": []
    },
    {
      "id": 4016,
      "post_author": 1,
      "post_date": "2026-07-18 10:00:00",
      "post_title": "हिन्दी शब्दकोश में 'क्ष' का क्रम इनमें से किस वर्ण के ...",
      "post_content": "हिन्दी शब्दकोश में 'क्ष' का क्रम इनमें से किस वर्ण के बाद में आता है ?",
      "post_status": "publish",
      "post_type": "question",
      "meta_input": {
        "_aimcq_options": [
          {
            "text": "ह",
            "image": ""
          },
          {
            "text": "छ",
            "image": ""
          },
          {
            "text": "क",
            "image": ""
          },
          {
            "text": "ष",
            "image": ""
          }
        ],
        "_aimcq_explanation": "<p>हिन्दी वर्णमाला में 'क्ष' एक संयुक्त व्यंजन है (क् + ष)। शब्दकोश में संयुक्त व्यंजनों को वर्णमाला के अंत में, स्वतंत्र वर्णों के बाद रखा जाता है।</p><p><b>विश्लेषण:</b> मानक हिन्दी वर्णमाला क्रम में स्वर और सभी व्यंजन (क से लेकर ह तक) आने के बाद संयुक्त व्यंजन क्ष, त्र, ज्ञ आते हैं। चूँकि 'क्ष' 'क्' और 'ष्' के मेल से बनता है, इसलिए शब्दकोश में यह सामान्यतः 'क' वर्ण के बाद (क वर्ग के अंत में) रखा जाता है।</p><p><b>अन्य विकल्प क्यों नहीं:</b> 'ह', 'छ' और 'ष' मूल वर्णमाला क्रम में अलग-अलग स्थान पर आते हैं, पर संयुक्ताक्षर 'क्ष' परंपरागत रूप से 'क' के तुरंत बाद स्थान पाता है।</p><p><b>याद रखने की तरकीब:</b> संयुक्त व्यंजन 'क्ष, त्र, ज्ञ' को क्रमशः क, त और ज वर्णों के निकट याद रखें। इसलिए सही उत्तर <b>'क'</b> है।</p>",
        "_aimcq_correct_answers": [
          2
        ]
      },
      "taxonomies": {
        "topic": [
          "hindi-vyakaran-uppsc-2021"
        ]
      },
      "embedded_media": []
    },
    {
      "id": 4017,
      "post_author": 1,
      "post_date": "2026-07-18 10:00:00",
      "post_title": "निम्नलिखित में तत्सम-तद्भव का शुद्ध युग्म है",
      "post_content": "निम्नलिखित में तत्सम-तद्भव का शुद्ध युग्म है",
      "post_status": "publish",
      "post_type": "question",
      "meta_input": {
        "_aimcq_options": [
          {
            "text": "नछत्र – नखत",
            "image": ""
          },
          {
            "text": "पक्वान्न – प्रकृवात्त",
            "image": ""
          },
          {
            "text": "गृद्ध – गीध",
            "image": ""
          },
          {
            "text": "अवश्याय – ओस",
            "image": ""
          }
        ],
        "_aimcq_explanation": "<p>तत्सम शब्द वे होते हैं जो संस्कृत से बिना बदलाव के हिन्दी में आए हैं, जबकि तद्भव वे शब्द हैं जो संस्कृत से रूप बदलकर हिन्दी में विकसित हुए हैं।</p><p><b>एक-एक विकल्प जाँचें:</b><br>- नछत्र – नखत → सही तत्सम रूप 'नक्षत्र' होता है, 'नछत्र' अशुद्ध रूप है ✘<br>- पक्वान्न – प्रकृवात्त → सही तत्सम रूप 'पक्वान्न' है, पर दिया गया तद्भव रूप मानक नहीं है ✘<br>- गृद्ध – गीध → सही तत्सम रूप 'गृध्र' होता है, 'गृद्ध' अशुद्ध रूप है ✘<br>- अवश्याय – ओस → 'अवश्याय' शुद्ध तत्सम शब्द है और इसका सही तद्भव रूप 'ओस' है ✔</p><p><b>याद रखने की तरकीब:</b> तत्सम-तद्भव जोड़ी जाँचते समय दोनों शब्दों की संस्कृत मूल वर्तनी को ध्यान से याद करें, ताकि हल्की-सी गलत वर्तनी पकड़ में आ सके। इसलिए सही उत्तर <b>'अवश्याय – ओस'</b> है।</p>",
        "_aimcq_correct_answers": [
          3
        ]
      },
      "taxonomies": {
        "topic": [
          "hindi-vyakaran-uppsc-2021"
        ]
      },
      "embedded_media": []
    },
    {
      "id": 4018,
      "post_author": 1,
      "post_date": "2026-07-18 10:00:00",
      "post_title": "निम्नलिखित में से किस शब्द में एकाधिक उपसर्गों का ...",
      "post_content": "निम्नलिखित में से किस शब्द में एकाधिक उपसर्गों का प्रयोग हुआ है ?",
      "post_status": "publish",
      "post_type": "question",
      "meta_input": {
        "_aimcq_options": [
          {
            "text": "अनुकरण",
            "image": ""
          },
          {
            "text": "निहत्था",
            "image": ""
          },
          {
            "text": "व्याकरण",
            "image": ""
          },
          {
            "text": "आगमन",
            "image": ""
          }
        ],
        "_aimcq_explanation": "<p>जब किसी शब्द में एक से अधिक उपसर्ग जुड़ें, तो उसे 'एकाधिक उपसर्ग' वाला शब्द कहते हैं।</p><p><b>एक-एक विकल्प जाँचें:</b><br>- अनुकरण → इसमें केवल एक उपसर्ग 'अनु' जुड़ा है (अनु + करण) ✘<br>- निहत्था → इसमें केवल एक उपसर्ग 'नि' जुड़ा है (नि + हत्था) ✘<br>- व्याकरण → यह शब्द 'वि' + 'आ' + 'करण' से बना है, यानी इसमें दो उपसर्ग ('वि' और 'आ') जुड़े हैं ✔<br>- आगमन → इसमें केवल एक उपसर्ग 'आ' जुड़ा है (आ + गमन) ✘</p><p><b>याद रखने की तरकीब:</b> 'व्याकरण' को तोड़ने पर 'वि + आ + करण' मिलता है, इसमें दो उपसर्गों का प्रयोग साफ़ दिखता है, जबकि बाकी शब्दों में एक ही उपसर्ग है। इसलिए सही उत्तर <b>'व्याकरण'</b> है।</p>",
        "_aimcq_correct_answers": [
          2
        ]
      },
      "taxonomies": {
        "topic": [
          "hindi-vyakaran-uppsc-2021"
        ]
      },
      "embedded_media": []
    },
    {
      "id": 4200,
      "post_author": 1,
      "post_date": "2026-07-18 10:00:00",
      "post_title": "अधोलिखित गद्यांश को ध्यान से पढ़िए तथा प्रश्न संख्या 19 ...",
      "post_content": "अधोलिखित गद्यांश को ध्यान से पढ़िए तथा प्रश्न संख्या 19 से 23 के उत्तर इस गद्यांश के आधार पर दीजिए ।<br><br>प्रकृति ने मानव जीवन को बहुत सरल बनाया है, किन्तु आज का मानव अपने जीवन-काल में ही पूरी दुनिया की सुख-समृद्धि बटोर लेने के प्रयास में उसको जटिल बनाता जा रहा है। इस जटिलता के कारण संसार में धनी-निर्धन, सत्ताधीश-सत्ताच्युत, संतानवान-निस्संतान सभी सुख-शान्ति की चाह तो रखते हैं, किन्तु राह पकड़ते हैं आह भरने की, मरु-मरीचिका के मैदान में जल की, धधकती आग में शीतलता की चाह रखते हैं । विद्वानों का विचार है कि संसार में सुख का मार्ग है – आत्मसंयम । किन्तु मानव इस मार्ग को भूलकर सांसारिक पदार्थों में, इन्द्रिय विषयों की प्राप्ति में आनन्द ढूँढ़ रहा है। परिणामतः दुःख के सागर में डूबता जा रहा है । आत्मसंयम का मार्ग अपने में बहुत स्पष्ट है, उसकी उपादेयता किसी भी काल में कम नहीं होती । इन्द्रिय विषयों का संयम ही आत्मसंयम है । भौतिक पदार्थों के प्रति इन्द्रियों का प्रबल आकर्षण मानवीय दुःखों का मूल कारण माना गया है । उपभोक्तावादी संस्कृति के फैलाव से यह आकर्षण दिन-प्रतिदिन तीव्रतर होता जा रहा है । पर ऐसी स्थिति में याद रखना आवश्यक है कि ये भौतिक पदार्थ सुख तो दे सकते हैं, आनन्द नहीं । आनन्द का निर्झर तो आत्मसंयम से फूटता है । उसकी मिठास अनिर्वचनीय और अनुपम होती है । इस मिठास के सम्मुख धन-संपत्ति, सत्ता, सौंदर्य का सुख, सागर के खारे पानी जैसा लगने लगता है ।",
      "post_status": "publish",
      "post_type": "passage",
      "meta_input": {
        "_aimcq_passage_content_hi": "",
        "_aimcq_passage_translation_custom_prompt": "",
        "_aimcq_passage_display_title_en": "अधोलिखित गद्यांश को ध्यान से पढ़िए तथा प्रश्न संख्या 19 से 23 के उत्तर इस गद्यांश के आधार पर दीजिए ।",
        "_aimcq_passage_display_title_hi": "",
        "_aimcq_explanation": ""
      },
      "taxonomies": [],
      "embedded_media": []
    },
    {
      "id": 4019,
      "post_author": 1,
      "post_date": "2026-07-18 10:00:00",
      "post_title": "आत्मसंयम का तात्पर्य है",
      "post_content": "आत्मसंयम का तात्पर्य है",
      "post_status": "publish",
      "post_type": "question",
      "meta_input": {
        "_aimcq_options": [
          {
            "text": "अपनी आत्मा पर नियंत्रण",
            "image": ""
          },
          {
            "text": "अपनी भावनाओं का नियमन",
            "image": ""
          },
          {
            "text": "अपने मन का वशीकरण",
            "image": ""
          },
          {
            "text": "इन्द्रियों के विषय के प्रति आकर्षण पर संयमन",
            "image": ""
          }
        ],
        "_aimcq_explanation": "<p><b>गद्यांश की मुख्य बात:</b> गद्यांश में 'आत्मसंयम' को सुख का मार्ग बताया गया है और उसकी परिभाषा भी स्पष्ट दी गई है।</p><p><b>सीधा उत्तर गद्यांश में:</b> गद्यांश में स्पष्ट लिखा है - \"इन्द्रिय विषयों का संयम ही आत्मसंयम है ।\" यानी इन्द्रियाँ जिन भौतिक विषयों की ओर आकर्षित होती हैं, उन पर नियंत्रण रखना ही आत्मसंयम कहलाता है।</p><p><b>बाकी विकल्प क्यों गलत:</b> गद्यांश में 'आत्मा पर नियंत्रण', 'भावनाओं के नियमन' या 'मन के वशीकरण' जैसे शब्दों का सीधा प्रयोग नहीं किया गया, बल्कि विशेष रूप से 'इन्द्रिय विषयों के संयम' की बात कही गई है।</p><p>इसलिए सही उत्तर <b>'इन्द्रियों के विषय के प्रति आकर्षण पर संयमन'</b> है।</p>",
        "_aimcq_is_passage_question": "yes",
        "_aimcq_passage_id": "4200",
        "_aimcq_correct_answers": [
          3
        ]
      },
      "taxonomies": {
        "topic": [
          "hindi-vyakaran-uppsc-2021"
        ]
      },
      "embedded_media": []
    },
    {
      "id": 4020,
      "post_author": 1,
      "post_date": "2026-07-18 10:00:00",
      "post_title": "सत्ताच्युत का सही वर्तनी विश्लेषण है",
      "post_content": "सत्ताच्युत का सही वर्तनी विश्लेषण है",
      "post_status": "publish",
      "post_type": "question",
      "meta_input": {
        "_aimcq_options": [
          {
            "text": "स् अ त् त आ च् अ य् उ त् अ",
            "image": ""
          },
          {
            "text": "स् अ त् त् आ च्&nbsp;य् उ त् अ",
            "image": ""
          },
          {
            "text": "स त् ता च् यु त",
            "image": ""
          },
          {
            "text": "स त् आ च् य् उ त् अ",
            "image": ""
          }
        ],
        "_aimcq_explanation": "<p>वर्तनी-विश्लेषण में किसी शब्द को उसकी मूल ध्वनियों (वर्णों और मात्राओं) में तोड़कर दिखाया जाता है।</p><p><b>विश्लेषण:</b> 'सत्ताच्युत' शब्द को उसके मूल वर्णों में तोड़ने पर बनता है - स् + अ + त् + त् + आ + च + य् + उ + त् + अ, यानी हर व्यंजन और स्वर को अलग-अलग सही क्रम में दिखाया जाता है।</p><p><b>अन्य विकल्प क्यों नहीं:</b> बाकी विकल्पों में या तो हलन्त (्) चिह्न सही जगह पर नहीं लगाया गया है, या कोई वर्ण/मात्रा छूट गई है या गलत क्रम में है, जिससे विश्लेषण अशुद्ध हो जाता है।</p><p><b>याद रखने की तरकीब:</b> वर्तनी-विश्लेषण करते समय हर संयुक्त व्यंजन (जैसे त्त, च्य) को उसके मूल दो अलग-अलग व्यंजनों में हलन्त सहित तोड़ें। इसलिए सही उत्तर <b>'स् अ त् त् आ च य् उ त् अ'</b> है।</p>",
        "_aimcq_is_passage_question": "yes",
        "_aimcq_passage_id": "4200",
        "_aimcq_correct_answers": [
          1
        ]
      },
      "taxonomies": {
        "topic": [
          "hindi-vyakaran-uppsc-2021"
        ]
      },
      "embedded_media": []
    },
    {
      "id": 4021,
      "post_author": 1,
      "post_date": "2026-07-18 10:00:00",
      "post_title": "आज का मानव जीवन को अधिक जटिल कैसे बना रहा है ?",
      "post_content": "आज का मानव जीवन को अधिक जटिल कैसे बना रहा है ?",
      "post_status": "publish",
      "post_type": "question",
      "meta_input": {
        "_aimcq_options": [
          {
            "text": "सुख-शान्ति की प्राप्ति के प्रयास में",
            "image": ""
          },
          {
            "text": "अपना यश फैलाने के प्रयत्न में",
            "image": ""
          },
          {
            "text": "संसार की सुख-समृद्धि को बटोरने के प्रयत्न में",
            "image": ""
          },
          {
            "text": "असीमित लालसाओं को पूरा करने की चाह में",
            "image": ""
          }
        ],
        "_aimcq_explanation": "<p><b>गद्यांश की मुख्य बात:</b> गद्यांश की शुरुआत में ही बताया गया है कि मानव जीवन को जटिल क्यों बना रहा है।</p><p><b>सीधा उत्तर गद्यांश में:</b> गद्यांश में लिखा है - \"आज का मानव अपने जीवन-काल में ही पूरी दुनिया की सुख-समृद्धि बटोर लेने के प्रयास में उसको जटिल बनाता जा रहा है ।\"</p><p><b>बाकी विकल्प क्यों गलत:</b> गद्यांश में यश फैलाने, सामान्य सुख-शान्ति पाने या असीमित लालसाओं का सीधा उल्लेख नहीं है, बल्कि विशेष रूप से 'सुख-समृद्धि बटोरने' के प्रयास की बात कही गई है।</p><p>इसलिए सही उत्तर <b>'संसार की सुख-समृद्धि को बटोरने के प्रयत्न में'</b> है।</p>",
        "_aimcq_is_passage_question": "yes",
        "_aimcq_passage_id": "4200",
        "_aimcq_correct_answers": [
          2
        ]
      },
      "taxonomies": {
        "topic": [
          "hindi-vyakaran-uppsc-2021"
        ]
      },
      "embedded_media": []
    },
    {
      "id": 4022,
      "post_author": 1,
      "post_date": "2026-07-18 10:00:00",
      "post_title": "गद्यांश के अनुसार भौतिक पदार्थ",
      "post_content": "गद्यांश के अनुसार भौतिक पदार्थ",
      "post_status": "publish",
      "post_type": "question",
      "meta_input": {
        "_aimcq_options": [
          {
            "text": "सुख दे सकते हैं और आनन्द दे सकते हैं",
            "image": ""
          },
          {
            "text": "केवल आनन्द दे सकते हैं",
            "image": ""
          },
          {
            "text": "न सुख दे सकते हैं और न आनन्द",
            "image": ""
          },
          {
            "text": "सुख दे सकते हैं किन्तु आनन्द नहीं",
            "image": ""
          }
        ],
        "_aimcq_explanation": "<p><b>गद्यांश की मुख्य बात:</b> गद्यांश के अंत में भौतिक पदार्थों की सीमा को स्पष्ट किया गया है।</p><p><b>सीधा उत्तर गद्यांश में:</b> गद्यांश में लिखा है - \"ये भौतिक पदार्थ सुख तो दे सकते हैं, आनन्द नहीं ।\" यानी भौतिक वस्तुएँ अस्थायी सुख तो दे सकती हैं, पर सच्चा आनन्द नहीं दे सकतीं।</p><p><b>बाकी विकल्प क्यों गलत:</b> गद्यांश में यह नहीं कहा गया कि भौतिक पदार्थ आनन्द देते हैं या दोनों देते हैं, न ही यह कहा गया कि वे कुछ भी नहीं दे सकते - स्पष्ट रूप से केवल 'सुख' देने की बात कही गई है, 'आनन्द' नहीं।</p><p>इसलिए सही उत्तर <b>'सुख दे सकते हैं किन्तु आनन्द नहीं'</b> है।</p>",
        "_aimcq_is_passage_question": "yes",
        "_aimcq_passage_id": "4200",
        "_aimcq_correct_answers": [
          3
        ]
      },
      "taxonomies": {
        "topic": [
          "hindi-vyakaran-uppsc-2021"
        ]
      },
      "embedded_media": []
    },
    {
      "id": 4023,
      "post_author": 1,
      "post_date": "2026-07-18 10:00:00",
      "post_title": "भौतिक पदार्थों के प्रति इन्द्रियों का प्रबल आकर्षण है",
      "post_content": "भौतिक पदार्थों के प्रति इन्द्रियों का प्रबल आकर्षण है",
      "post_status": "publish",
      "post_type": "question",
      "meta_input": {
        "_aimcq_options": [
          {
            "text": "मानवीय करुणा का कारण",
            "image": ""
          },
          {
            "text": "मानवीय सुखों का मूल कारण",
            "image": ""
          },
          {
            "text": "अमानवीय कृत्यों का कारण",
            "image": ""
          },
          {
            "text": "मानवीय दुःखों का मूल कारण",
            "image": ""
          }
        ],
        "_aimcq_explanation": "<p><b>गद्यांश की मुख्य बात:</b> गद्यांश में भौतिक पदार्थों के प्रति इन्द्रियों के आकर्षण को दुःख से जोड़ा गया है।</p><p><b>सीधा उत्तर गद्यांश में:</b> गद्यांश में स्पष्ट लिखा है - \"भौतिक पदार्थों के प्रति इन्द्रियों का प्रबल आकर्षण मानवीय दुःखों का मूल कारण माना गया है ।\"</p><p><b>बाकी विकल्प क्यों गलत:</b> गद्यांश में इसे करुणा, सुखों या अमानवीय कृत्यों का कारण नहीं बताया गया, बल्कि सीधे-सीधे 'मानवीय दुःखों का मूल कारण' कहा गया है।</p><p>इसलिए सही उत्तर <b>'मानवीय दुःखों का मूल कारण'</b> है।</p>",
        "_aimcq_is_passage_question": "yes",
        "_aimcq_passage_id": "4200",
        "_aimcq_correct_answers": [
          3
        ]
      },
      "taxonomies": {
        "topic": [
          "hindi-vyakaran-uppsc-2021"
        ]
      },
      "embedded_media": []
    }
  ]
}